[{"id":9687,"title":"The Odyssey","year":1997,"aliases":["The Odyssey Armand Assante"]},{"id":791373,"title":"The Odyssey","year":2026,"aliases":["The Odyssey Christopher Nolan"]},{"id":62,"title":"2001: A Space Odyssey","year":1968},{"id":157336,"title":"Interstellar","year":2014},{"id":329865,"title":"Arrival","year":2016},{"id":686,"title":"Contact","year":1997},{"id":78,"title":"Blade Runner","year":1982},{"id":335984,"title":"Blade Runner 2049","year":2017},{"id":593,"title":"Solaris","year":1972},{"id":1398,"title":"Stalker","year":1979},{"id":603,"title":"The Matrix","year":1999},{"id":27205,"title":"Inception","year":2010},{"id":264660,"title":"Ex Machina","year":2015},{"id":300668,"title":"Annihilation","year":2018},{"id":782,"title":"Gattaca","year":1997},{"id":9693,"title":"Children of Men","year":2006},{"id":152601,"title":"Her","year":2013},{"id":38,"title":"Eternal Sunshine of the Spotless Mind","year":2004},{"id":545611,"title":"Everything Everywhere All at Once","year":2022,"aliases":["EEAAO"]},{"id":438631,"title":"Dune","year":2021},{"id":693134,"title":"Dune: Part Two","year":2024,"aliases":["Dune 2"]},{"id":17431,"title":"Moon","year":2009},{"id":17654,"title":"District 9","year":2009},{"id":286217,"title":"The Martian","year":2015},{"id":1272,"title":"Sunshine","year":2007},{"id":840,"title":"Close Encounters of the Third Kind","year":1977},{"id":871,"title":"Planet of the Apes","year":1968},{"id":37165,"title":"The Truman Show","year":1998},{"id":1124,"title":"The Prestige","year":2006},{"id":77,"title":"Memento","year":2000},{"id":872585,"title":"Oppenheimer","year":2023},{"id":7345,"title":"There Will Be Blood","year":2007},{"id":6977,"title":"No Country for Old Men","year":2007},{"id":278,"title":"The Shawshank Redemption","year":1994},{"id":510,"title":"One Flew Over the Cuckoo's Nest","year":1975},{"id":497,"title":"The Green Mile","year":1999},{"id":424,"title":"Schindler's List","year":1993},{"id":582,"title":"The Lives of Others","year":2006},{"id":496243,"title":"Parasite","year":2019},{"id":600354,"title":"The Father","year":2020},{"id":965150,"title":"Aftersun","year":2022},{"id":674324,"title":"The Banshees of Inisherin","year":2022},{"id":792307,"title":"Poor Things","year":2023},{"id":467244,"title":"The Zone of Interest","year":2023},{"id":915935,"title":"Anatomy of a Fall","year":2023},{"id":947,"title":"Lawrence of Arabia","year":1962},{"id":665,"title":"Ben-Hur","year":1959},{"id":967,"title":"Spartacus","year":1960},{"id":98,"title":"Gladiator","year":2000},{"id":279,"title":"Amadeus","year":1984},{"id":3175,"title":"Barry Lyndon","year":1975},{"id":746,"title":"The Last Emperor","year":1987},{"id":9361,"title":"The Last of the Mohicans","year":1992},{"id":8619,"title":"Master and Commander: The Far Side of the World","year":2003,"aliases":["Master and Commander"]},{"id":120,"title":"The Lord of the Rings: The Fellowship of the Ring","year":2001,"aliases":["LOTR Fellowship"]},{"id":121,"title":"The Lord of the Rings: The Two Towers","year":2002,"aliases":["LOTR Two Towers"]},{"id":122,"title":"The Lord of the Rings: The Return of the King","year":2003,"aliases":["LOTR Return of the King"]},{"id":11,"title":"Star Wars: Episode IV – A New Hope","year":1977,"aliases":["Star Wars A New Hope","Episode IV"]},{"id":1891,"title":"Star Wars: Episode V – The Empire Strikes Back","year":1980,"aliases":["The Empire Strikes Back","Episode V"]},{"id":1892,"title":"Star Wars: Episode VI – Return of the Jedi","year":1983,"aliases":["Return of the Jedi","Episode VI"]},{"id":1893,"title":"Star Wars: Episode I – The Phantom Menace","year":1999,"aliases":["The Phantom Menace","Episode I"]},{"id":1894,"title":"Star Wars: Episode II – Attack of the Clones","year":2002,"aliases":["Attack of the Clones","Episode II"]},{"id":1895,"title":"Star Wars: Episode III – Revenge of the Sith","year":2005,"aliases":["Revenge of the Sith","Episode III"]},{"id":12180,"title":"Star Wars: The Clone Wars","year":2008,"aliases":["The Clone Wars movie"]},{"id":140607,"title":"Star Wars: Episode VII – The Force Awakens","year":2015,"aliases":["The Force Awakens","Episode VII"]},{"id":330459,"title":"Rogue One: A Star Wars Story","year":2016,"aliases":["Rogue One"]},{"id":181808,"title":"Star Wars: Episode VIII – The Last Jedi","year":2017,"aliases":["The Last Jedi","Episode VIII"]},{"id":348350,"title":"Solo: A Star Wars Story","year":2018,"aliases":["Solo"]},{"id":181812,"title":"Star Wars: Episode IX – The Rise of Skywalker","year":2019,"aliases":["The Rise of Skywalker","Episode IX"]},{"id":152,"title":"Star Trek: The Motion Picture","year":1979},{"id":154,"title":"Star Trek II: The Wrath of Khan","year":1982,"aliases":["The Wrath of Khan"]},{"id":157,"title":"Star Trek III: The Search for Spock","year":1984,"aliases":["The Search for Spock"]},{"id":168,"title":"Star Trek IV: The Voyage Home","year":1986,"aliases":["The Voyage Home"]},{"id":174,"title":"Star Trek V: The Final Frontier","year":1989,"aliases":["The Final Frontier"]},{"id":172,"title":"Star Trek VI: The Undiscovered Country","year":1991,"aliases":["The Undiscovered Country"]},{"id":193,"title":"Star Trek: Generations","year":1994},{"id":199,"title":"Star Trek: First Contact","year":1996},{"id":200,"title":"Star Trek: Insurrection","year":1998},{"id":201,"title":"Star Trek: Nemesis","year":2002},{"id":13475,"title":"Star Trek","year":2009,"aliases":["Star Trek 2009"]},{"id":54138,"title":"Star Trek Into Darkness","year":2013},{"id":188927,"title":"Star Trek Beyond","year":2016},{"id":454,"title":"Romeo + Juliet","year":1996,"aliases":["William Shakespeare's Romeo + Juliet"]},{"id":6003,"title":"Romeo and Juliet","year":1968,"aliases":["Franco Zeffirelli Romeo and Juliet"]},{"id":137094,"title":"Romeo & Juliet","year":2013},{"id":10549,"title":"Hamlet","year":1996,"aliases":["Kenneth Branagh Hamlet"]},{"id":11635,"title":"Hamlet","year":1990,"aliases":["Mel Gibson Hamlet"]},{"id":225728,"title":"Macbeth","year":2015},{"id":541134,"title":"The Tragedy of Macbeth","year":2021},{"id":9800,"title":"Othello","year":1995},{"id":502728,"title":"King Lear","year":2018},{"id":11971,"title":"Much Ado About Nothing","year":1993},{"id":38150,"title":"The Tempest","year":2010},{"id":9827,"title":"Julius Caesar","year":1953}]